renovo/__init__.py
renovo/__main__.py
renovo/dependency_tracker.py
renovo/hot_module_replacement.py
renovo-0.2.0.dist-info/licenses/LICENSE
renovo-0.2.0.dist-info/WHEEL
renovo-0.2.0.dist-info/METADATA
renovo-0.2.0.dist-info/RECORD
