Metadata-Version: 2.4
Name: renovo
Version: 0.2.0
Summary: 
Requires-Python: >=3.7
Classifier: Programming Language :: Python :: 3
Classifier: Programming Language :: Python :: 3 :: Only
Classifier: Programming Language :: Python :: 3.7
Classifier: Programming Language :: Python :: 3.8
Classifier: Programming Language :: Python :: 3.9
Classifier: Programming Language :: Python :: 3.10
Classifier: Programming Language :: Python :: 3.11
Classifier: Programming Language :: Python :: 3.12
License-File: LICENSE
Requires-Dist: flit ; extra == "dev"
Requires-Dist: tbump ; extra == "dev"
Requires-Dist: uv ; extra == "dev"
Requires-Dist: pre-commit ; extra == "dev"
Requires-Dist: pytest ; extra == "test"
Requires-Dist: pytest-cov ; extra == "test"
Requires-Dist: ruff>=0.5,<0.6 ; extra == "test"
Provides-Extra: dev
Provides-Extra: test
